<annotation>
	<folder>train</folder>
	<filename>1066.jpg</filename>
	<path>C:\traffic_counter\data\images\train\1066.jpg</path>
	<source>
		<database>Unknown</database>
	</source>
	<size>
		<width>800</width>
		<height>600</height>
		<depth>3</depth>
	</size>
	<segmented>0</segmented>
	<object>
		<name>car</name>
		<pose>Unspecified</pose>
		<truncated>0</truncated>
		<difficult>0</difficult>
		<bndbox>
			<xmin>553</xmin>
			<ymin>245</ymin>
			<xmax>688</xmax>
			<ymax>318</ymax>
		</bndbox>
	</object>
	<object>
		<name>car</name>
		<pose>Unspecified</pose>
		<truncated>0</truncated>
		<difficult>0</difficult>
		<bndbox>
			<xmin>314</xmin>
			<ymin>257</ymin>
			<xmax>378</xmax>
			<ymax>301</ymax>
		</bndbox>
	</object>
	<object>
		<name>car</name>
		<pose>Unspecified</pose>
		<truncated>0</truncated>
		<difficult>0</difficult>
		<bndbox>
			<xmin>109</xmin>
			<ymin>258</ymin>
			<xmax>166</xmax>
			<ymax>301</ymax>
		</bndbox>
	</object>
</annotation>
