<annotation>
	<folder>train</folder>
	<filename>108.jpg</filename>
	<path>C:\traffic_counter\data\images\train\108.jpg</path>
	<source>
		<database>Unknown</database>
	</source>
	<size>
		<width>800</width>
		<height>600</height>
		<depth>3</depth>
	</size>
	<segmented>0</segmented>
	<object>
		<name>suv</name>
		<pose>Unspecified</pose>
		<truncated>0</truncated>
		<difficult>0</difficult>
		<bndbox>
			<xmin>350</xmin>
			<ymin>237</ymin>
			<xmax>450</xmax>
			<ymax>303</ymax>
		</bndbox>
	</object>
	<object>
		<name>van</name>
		<pose>Unspecified</pose>
		<truncated>0</truncated>
		<difficult>0</difficult>
		<bndbox>
			<xmin>242</xmin>
			<ymin>232</ymin>
			<xmax>321</xmax>
			<ymax>297</ymax>
		</bndbox>
	</object>
</annotation>
